{
    "16": {
        "16.0v9": {
            "installer": {
                "mac_arm": "https://thefoundry.s3.amazonaws.com/products/nuke/releases/16.0v9/Nuke16.0v9-mac-arm64.dmg",
                "mac_x86_64": "https://thefoundry.s3.amazonaws.com/products/nuke/releases/16.0v9/Nuke16.0v9-mac-x86_64.dmg",
                "linux_x86_64": null,
                "windows_x86_64": "https://thefoundry.s3.amazonaws.com/products/nuke/releases/16.0v9/Nuke16.0v9-win-x86_64.zip"
            },
            "date": "Thu, 02 Apr 2026 10:22:11 GMT",
            "supported": true
        }
    },
    "15": {
        "15.2v1": {
            "installer": {
                "mac_arm": "https://thefoundry.s3.amazonaws.com/products/nuke/releases/15.2v1/Nuke15.2v1-mac-arm64.dmg",
                "mac_x86_64": "https://thefoundry.s3.amazonaws.com/products/nuke/releases/15.2v1/Nuke15.2v1-mac-x86_64.dmg",
                "linux_x86_64": "https://thefoundry.s3.amazonaws.com/products/nuke/releases/15.2v1/Nuke15.2v1-linux-x86_64.tgz",
                "windows_x86_64": "https://thefoundry.s3.amazonaws.com/products/nuke/releases/15.2v1/Nuke15.2v1-win-x86_64.zip"
            },
            "date": "Wed, 26 Feb 2025 10:28:13 GMT",
            "supported": true
        }
    }
}